custom_ui_package/__init__.py
custom_ui_package/custom_accordion.py
custom_ui_package/custom_badge.py
custom_ui_package/custom_button.py
custom_ui_package/custom_card.py
custom_ui_package/custom_checkbox.py
custom_ui_package/custom_dialog.py
custom_ui_package/custom_dropdown.py
custom_ui_package/custom_input_box.py
custom_ui_package/custom_label.py
custom_ui_package/custom_main_window.py
custom_ui_package/custom_menu.py
custom_ui_package/custom_modal.py
custom_ui_package/custom_progressbar.py
custom_ui_package/custom_radiobutton.py
custom_ui_package/custom_scrollbar.py
custom_ui_package/custom_slider.py
custom_ui_package/custom_spinner.py
custom_ui_package/custom_tabwidget.py
custom_ui_package/custom_textarea.py
custom_ui_package/custom_titlebar.py
custom_ui_package/custom_toast.py
custom_ui_package/custom_tooltip.py
custom_ui_package/colors/__init__.py
custom_ui_package/colors/color_palette.py
custom_ui_pyqt6-1.0.7.dist-info/licenses/LICENSE
custom_ui_pyqt6-1.0.7.dist-info/METADATA
custom_ui_pyqt6-1.0.7.dist-info/WHEEL
custom_ui_pyqt6-1.0.7.dist-info/top_level.txt
custom_ui_pyqt6-1.0.7.dist-info/RECORD
