Metadata-Version: 2.4
Name: custom-ui-pyqt6
Version: 1.0.7
Summary: Modern PyQt6 UI components with glassmorphism effects, smooth animations, and 22 customizable widgets
Home-page: https://github.com/CrypterENC/custom-ui-pyqt6
Author: CrypterENC
Author-email: a95899003@gmail.com
Project-URL: Bug Reports, https://github.com/CrypterENC/custom--pyqt6--ui/issues
Project-URL: Documentation, https://github.com/CrypterENC/custom--pyqt6--ui#readme
Project-URL: Examples, https://github.com/CrypterENC/custom--pyqt6--ui/blob/main/DOCUMENTATION.md#examples
Keywords: pyqt6,qt6,ui,gui,components,widgets,glassmorphism,modern,design,animations,buttons,forms,dialogs,menus,scrollbars,textarea,checkbox,radiobutton,slider,progressbar,tabs,cards,badges,spinner,toast,tooltip,accordion,frameless,customizable,themeable,solid-colors,desktop-application,cross-platform
Classifier: Programming Language :: Python :: 3
Classifier: Programming Language :: Python :: 3.8
Classifier: Programming Language :: Python :: 3.9
Classifier: Programming Language :: Python :: 3.10
Classifier: Programming Language :: Python :: 3.11
Classifier: Programming Language :: Python :: 3.12
Classifier: Programming Language :: Python :: 3.13
Classifier: Operating System :: OS Independent
Classifier: Development Status :: 5 - Production/Stable
Classifier: Intended Audience :: Developers
Classifier: License :: OSI Approved :: MIT License
Classifier: Topic :: Software Development :: Libraries :: Python Modules
Classifier: Topic :: Software Development :: User Interfaces
Classifier: Topic :: Desktop Environment :: Window Managers
Classifier: Intended Audience :: Information Technology
Classifier: Natural Language :: English
Requires-Python: >=3.8
License-File: LICENSE
Requires-Dist: PyQt6>=6.0.0
Dynamic: author
Dynamic: author-email
Dynamic: classifier
Dynamic: description
Dynamic: description-content-type
Dynamic: home-page
Dynamic: keywords
Dynamic: license-file
Dynamic: project-url
Dynamic: requires-dist
Dynamic: requires-python
Dynamic: summary
